.gitignore
CHANGES.rst
LICENSE
MANIFEST.in
README.rst
setup.py
tox.ini
.github/workflows/release.yml
.github/workflows/tests.yml
docs/conf.py
docs/index.rst
docs/_specs/github.yml
docs/_static/logo.png
sphinxcontrib/__init__.py
sphinxcontrib/redoc.j2
sphinxcontrib/redoc.js
sphinxcontrib/redoc.py
sphinxcontrib_redoc.egg-info/PKG-INFO
sphinxcontrib_redoc.egg-info/SOURCES.txt
sphinxcontrib_redoc.egg-info/dependency_links.txt
sphinxcontrib_redoc.egg-info/namespace_packages.txt
sphinxcontrib_redoc.egg-info/not-zip-safe
sphinxcontrib_redoc.egg-info/requires.txt
sphinxcontrib_redoc.egg-info/top_level.txt
tests/test_integration.py