Metadata-Version: 1.1
Name: sphinxcontrib-redoc
Version: 1.6.0
Summary: ReDoc powered OpenAPI (fka Swagger) spec renderer for Sphinx
Home-page: https://github.com/ikalnytskyi/sphinxcontrib-redoc
Author: Ihor Kalnytskyi
Author-email: ihor@kalnytskyi.com
License: BSD
Keywords: sphinx openapi swagger rest api renderer docs redoc
Platform: UNKNOWN
Classifier: Topic :: Documentation
Classifier: License :: OSI Approved :: BSD License
Classifier: Environment :: Console
Classifier: Intended Audience :: Developers
Classifier: Operating System :: OS Independent
Classifier: Programming Language :: Python
Classifier: Programming Language :: Python :: 2
Classifier: Programming Language :: Python :: 2.7
Classifier: Programming Language :: Python :: 3
Classifier: Programming Language :: Python :: 3.5
Classifier: Programming Language :: Python :: 3.6
Classifier: Programming Language :: Python :: 3.7
Classifier: Programming Language :: Python :: 3.8
